t5_grp/__init__.py
t5_grp/assets/favicon.ico
t5_grp/assets/main.css
t5_grp/assets/main.js
t5_grp/config.py
t5_grp/main.py
t5_grp/parser/yaml_parser.py
t5_grp/templates/pipeline_template.html
t5_grp/templates/yaml_viewer_template.html
t5_grp/visualization/diagram_generator.py
tests/__init__.py
tests/page/__init__.py
tests/page/element.py
tests/page/locators.py
tests/page/page.py
tests/parser/test_yaml_parser.py
tests/test_files/invalid.yaml
tests/test_files/test.yaml
tests/test_files/valid.yaml
tests/test_main.py
tests/test_page.py
tests/visualization/test_diagram_generator.py
t5_grp-0.1.1.dist-info/METADATA
t5_grp-0.1.1.dist-info/WHEEL
t5_grp-0.1.1.dist-info/entry_points.txt
t5_grp-0.1.1.dist-info/RECORD
