Metadata-Version: 2.1
Name: t5_grp
Version: 0.1.1
Summary: A tool to generate and visualize pipeline diagrams
License: MIT
Author: Yoyo
Author-email: wu.yuanyu@northeastern.edu
Requires-Python: >=3.12,<4.0
Classifier: License :: OSI Approved :: MIT License
Classifier: Programming Language :: Python :: 3
Classifier: Programming Language :: Python :: 3.12
Requires-Dist: jinja2 (>=3.1.4,<4.0.0)
Requires-Dist: pyyaml (>=6.0.2,<7.0.0)
Requires-Dist: selenium (>=4.26.1,<5.0.0)
